vk_dev/DotDict.py
vk_dev/__init__.py
vk_dev/__main__.py
vk_dev/api.py
vk_dev/condition.py
vk_dev/dot_dict.py
vk_dev/exception.py
vk_dev/payload.py
vk_dev/tools.py
vk_dev/upload.py
vk_dev/vk.py
vk_dev/vkui.py
vk_dev/cond/__init__.py
vk_dev/cond/by.py
vk_dev/cond/path.py
vk_dev/cond/payload.py
vk_dev/cond/prefix.py
vk_dev-3.0.1.dist-info/LICENSE
vk_dev-3.0.1.dist-info/METADATA
vk_dev-3.0.1.dist-info/WHEEL
vk_dev-3.0.1.dist-info/top_level.txt
vk_dev-3.0.1.dist-info/RECORD
